CUB_financial_calculator/__init__.py
CUB_financial_calculator/calculator.py
CUB_financial_calculator/cli.py
CUB_financial_calculator-0.1.dist-info/METADATA
CUB_financial_calculator-0.1.dist-info/WHEEL
CUB_financial_calculator-0.1.dist-info/entry_points.txt
CUB_financial_calculator-0.1.dist-info/top_level.txt
CUB_financial_calculator-0.1.dist-info/RECORD
