Metadata-Version: 2.1
Name: CUB_financial_calculator
Version: 0.1
Summary: A package for calculating financial metrics like net profit and ROI.
Author: Alex
Author-email: haylarrr@yandex.ru
